pagtest/__init__.py
pagtest/setup.py
pagtest/test1.py
pagtest/test2.py
pagtest/test3.py
huangzilong000000001-1.0.0.dist-info/METADATA
huangzilong000000001-1.0.0.dist-info/WHEEL
huangzilong000000001-1.0.0.dist-info/top_level.txt
huangzilong000000001-1.0.0.dist-info/RECORD
