Metadata-Version: 2.1
Name: huangzilong000000001
Version: 1.0.0
Summary: A print test for PyPI
Home-page: UNKNOWN
Author: huangzilong
Author-email: 371007354@qq.com
License: MIT
Keywords: ga nn
Platform: UNKNOWN
Requires-Python: >=3
